{"nodes": [{"id": "daemon_scheduler_mjs", "label": "scheduler.mjs", "file_type": "code", "source_file": "daemon/scheduler.mjs", "source_location": "L1"}, {"id": "scheduler_initscheduler", "label": "initScheduler()", "file_type": "code", "source_file": "daemon/scheduler.mjs", "source_location": "L31"}], "edges": [{"source": "daemon_scheduler_mjs", "target": "child_process", "relation": "imports_from", "confidence": "EXTRACTED", "source_file": "daemon/scheduler.mjs", "source_location": "L8", "weight": 1.0}, {"source": "daemon_scheduler_mjs", "target": "util", "relation": "imports_from", "confidence": "EXTRACTED", "source_file": "daemon/scheduler.mjs", "source_location": "L9", "weight": 1.0}, {"source": "daemon_scheduler_mjs", "target": "node_cron", "relation": "imports_from", "confidence": "EXTRACTED", "source_file": "daemon/scheduler.mjs", "source_location": "L10", "weight": 1.0}, {"source": "daemon_scheduler_mjs", "target": "daemon_orchestrator_mjs", "relation": "imports_from", "confidence": "EXTRACTED", "source_file": "daemon/scheduler.mjs", "source_location": "L11", "weight": 1.0}, {"source": "daemon_scheduler_mjs", "target": "daemon_ingestion_mjs", "relation": "imports_from", "confidence": "EXTRACTED", "source_file": "daemon/scheduler.mjs", "source_location": "L12", "weight": 1.0}, {"source": "daemon_scheduler_mjs", "target": "daemon_processors_obsolescence_detector_mjs", "relation": "imports_from", "confidence": "EXTRACTED", "source_file": "daemon/scheduler.mjs", "source_location": "L13", "weight": 1.0}, {"source": "daemon_scheduler_mjs", "target": "daemon_config_env_mjs", "relation": "imports_from", "confidence": "EXTRACTED", "source_file": "daemon/scheduler.mjs", "source_location": "L14", "weight": 1.0}, {"source": "daemon_scheduler_mjs", "target": "scheduler_initscheduler", "relation": "contains", "confidence": "EXTRACTED", "source_file": "daemon/scheduler.mjs", "source_location": "L31", "weight": 1.0}], "raw_calls": [{"caller_nid": "scheduler_initscheduler", "callee": "log", "source_file": "daemon/scheduler.mjs", "source_location": "L32"}, {"caller_nid": "scheduler_initscheduler", "callee": "schedule", "source_file": "daemon/scheduler.mjs", "source_location": "L35"}, {"caller_nid": "scheduler_initscheduler", "callee": "schedule", "source_file": "daemon/scheduler.mjs", "source_location": "L49"}, {"caller_nid": "scheduler_initscheduler", "callee": "schedule", "source_file": "daemon/scheduler.mjs", "source_location": "L86"}, {"caller_nid": "scheduler_initscheduler", "callee": "schedule", "source_file": "daemon/scheduler.mjs", "source_location": "L133"}, {"caller_nid": "scheduler_initscheduler", "callee": "schedule", "source_file": "daemon/scheduler.mjs", "source_location": "L172"}, {"caller_nid": "scheduler_initscheduler", "callee": "schedule", "source_file": "daemon/scheduler.mjs", "source_location": "L201"}, {"caller_nid": "scheduler_initscheduler", "callee": "schedule", "source_file": "daemon/scheduler.mjs", "source_location": "L238"}, {"caller_nid": "scheduler_initscheduler", "callee": "log", "source_file": "daemon/scheduler.mjs", "source_location": "L257"}, {"caller_nid": "scheduler_initscheduler", "callee": "log", "source_file": "daemon/scheduler.mjs", "source_location": "L258"}, {"caller_nid": "scheduler_initscheduler", "callee": "log", "source_file": "daemon/scheduler.mjs", "source_location": "L259"}, {"caller_nid": "scheduler_initscheduler", "callee": "log", "source_file": "daemon/scheduler.mjs", "source_location": "L260"}, {"caller_nid": "scheduler_initscheduler", "callee": "log", "source_file": "daemon/scheduler.mjs", "source_location": "L261"}, {"caller_nid": "scheduler_initscheduler", "callee": "log", "source_file": "daemon/scheduler.mjs", "source_location": "L262"}, {"caller_nid": "scheduler_initscheduler", "callee": "log", "source_file": "daemon/scheduler.mjs", "source_location": "L263"}, {"caller_nid": "scheduler_initscheduler", "callee": "log", "source_file": "daemon/scheduler.mjs", "source_location": "L265"}]}